odoo10_addon_product_expiry_simple-10.0.1.0.1.99.dev2-py3.8-nspkg.pth
odoo/addons/product_expiry_simple/README.rst
odoo/addons/product_expiry_simple/__init__.py
odoo/addons/product_expiry_simple/__manifest__.py
odoo/addons/product_expiry_simple/data/product_removal.xml
odoo/addons/product_expiry_simple/i18n/de.po
odoo/addons/product_expiry_simple/i18n/es.po
odoo/addons/product_expiry_simple/i18n/fr.po
odoo/addons/product_expiry_simple/i18n/hr.po
odoo/addons/product_expiry_simple/i18n/it.po
odoo/addons/product_expiry_simple/i18n/nl_NL.po
odoo/addons/product_expiry_simple/i18n/product_expiry_simple.pot
odoo/addons/product_expiry_simple/i18n/pt.po
odoo/addons/product_expiry_simple/i18n/sl.po
odoo/addons/product_expiry_simple/models/__init__.py
odoo/addons/product_expiry_simple/models/stock_production_lot.py
odoo/addons/product_expiry_simple/models/stock_quant.py
odoo/addons/product_expiry_simple/static/description/icon.png
odoo/addons/product_expiry_simple/views/stock.xml
odoo10_addon_product_expiry_simple-10.0.1.0.1.99.dev2.dist-info/METADATA
odoo10_addon_product_expiry_simple-10.0.1.0.1.99.dev2.dist-info/WHEEL
odoo10_addon_product_expiry_simple-10.0.1.0.1.99.dev2.dist-info/namespace_packages.txt
odoo10_addon_product_expiry_simple-10.0.1.0.1.99.dev2.dist-info/top_level.txt
odoo10_addon_product_expiry_simple-10.0.1.0.1.99.dev2.dist-info/RECORD
